tikv_client-0.0.4.dist-info/METADATA
tikv_client-0.0.4.dist-info/WHEEL
tikv_client-0.0.4.dist-info/license_files/LICENSE
tikv_client/asynchronous/__init__.py
tikv_client/__init__.py
tikv_client/tikv_client.cpython-311-x86_64-linux-gnu.so
tikv_client-0.0.4.dist-info/RECORD
