Metadata-Version: 2.1
Name: tikv_client
Version: 0.0.4
Requires-Dist: pytest ~=7.4.2 ; extra == 'test'
Requires-Dist: pytest-asyncio ~=0.21.1 ; extra == 'test'
Provides-Extra: test
License-File: LICENSE
Summary: TiKV Client for Python
Keywords: TiKV
Author: Andy Lok <andylokandy@hotmail.com>
Author-email: Andy Lok <andylokandy@hotmail.com>
Maintainer-email: Andy Lok <andylokandy@hotmail.com>
Requires-Python: >=3.6
